agentcurie/__init__.py
agentcurie/logging_config.py
agentcurie/controller/__init__.py
agentcurie/controller/service.py
agentcurie/controller/tests.py
agentcurie/controller/utils.py
agentcurie/controller/views.py
agentcurie/controller/agent/__init__.py
agentcurie/controller/agent/service.py
agentcurie/controller/agent/tests.py
agentcurie/controller/agent/utils.py
agentcurie/controller/agent/views.py
agentcurie/controller/agent/registery/service.py
agentcurie/controller/agent/registery/views.py
agentcurie/controller/tool/__init__.py
agentcurie/controller/tool/service.py
agentcurie/controller/tool/tests.py
agentcurie/controller/tool/tool_views.py
agentcurie/controller/tool/views.py
agentcurie/controller/tool/registery/service.py
agentcurie/controller/tool/registery/views.py
agentcurie/mcp_client/__init__.py
agentcurie/mcp_client/service.py
agentcurie/mcp_client/examples/file_managing.py
agentcurie/supervisor/__init__.py
agentcurie/supervisor/prompts.py
agentcurie/supervisor/service.py
agentcurie/supervisor/utils.py
agentcurie/supervisor/views.py
agentcurie/supervisor/message_manager/__init__.py
agentcurie/supervisor/message_manager/service.py
agentcurie/supervisor/message_manager/views.py
agentcurie-0.1.2.dist-info/licenses/LICENSE
agentcurie-0.1.2.dist-info/METADATA
agentcurie-0.1.2.dist-info/WHEEL
agentcurie-0.1.2.dist-info/top_level.txt
agentcurie-0.1.2.dist-info/RECORD
