Metadata-Version: 2.4
Name: agentcurie
Version: 0.1.2
Summary: Multiagentic supervisory system
Author-email: Afreedi Z <afreedisulfiker@gmail.com>
License: The MIT License (MIT)
Project-URL: Homepage, https://github.com/afreediz/agentcurie
Project-URL: Issues, https://github.com/afreediz/agentcurie/issues
Requires-Python: >=3.9
License-File: LICENSE
Requires-Dist: requests>=2.28
Requires-Dist: langchain>=1.2.0
Requires-Dist: langchain-core>=1.2.5
Requires-Dist: pydantic>=2.12.5
Requires-Dist: mcp>=1.25.0
Dynamic: license-file
